prometheus_pysunspec2_exporter/__init__.py
prometheus_pysunspec2_exporter/collector.py
prometheus_pysunspec2_exporter/config.py
prometheus_pysunspec2_exporter/prometheus_metrics.py
prometheus_pysunspec2_exporter/run.py
prometheus_pysunspec2_exporter/sunspec.py
prometheus_pysunspec2_exporter-0.0.3.dist-info/licenses/LICENCE
prometheus_pysunspec2_exporter-0.0.3.dist-info/METADATA
prometheus_pysunspec2_exporter-0.0.3.dist-info/WHEEL
prometheus_pysunspec2_exporter-0.0.3.dist-info/entry_points.txt
prometheus_pysunspec2_exporter-0.0.3.dist-info/top_level.txt
prometheus_pysunspec2_exporter-0.0.3.dist-info/RECORD
