Metadata-Version: 2.4
Name: prometheus_pysunspec2_exporter
Version: 0.0.3
Summary: A Prometheus exporter for sunspec devices based on pySunSpec2.
License:                     GNU GENERAL PUBLIC LICENSE
License-File: LICENCE
Requires-Dist: pysunspec2
Requires-Dist: pyyaml
Requires-Dist: prometheus-client
Requires-Dist: pyserial
Dynamic: license-file
